sppl/__init__.py
sppl/distributions.py
sppl/dnf.py
sppl/math_util.py
sppl/poly.py
sppl/render.py
sppl/sets.py
sppl/spe.py
sppl/sym_util.py
sppl/timeout.py
sppl/transforms.py
sppl/compilers/__init__.py
sppl/compilers/ast_to_spe.py
sppl/compilers/spe_to_dict.py
sppl/compilers/spe_to_sppl.py
sppl/compilers/sppl_to_python.py
sppl/magics/__init__.py
sppl/magics/magics.py
sppl/magics/render.py
sppl/tests/__init__.py
sppl/tests/test_ast_condition.py
sppl/tests/test_ast_for.py
sppl/tests/test_ast_ifelse.py
sppl/tests/test_ast_switch.py
sppl/tests/test_ast_transform.py
sppl/tests/test_burglary.py
sppl/tests/test_cache_duplicate_subtrees.py
sppl/tests/test_clickgraph.py
sppl/tests/test_dnf.py
sppl/tests/test_event_evaluate.py
sppl/tests/test_indian_gpa.py
sppl/tests/test_logpdf.py
sppl/tests/test_mutual_information.py
sppl/tests/test_nominal_distribution.py
sppl/tests/test_parse_distributions.py
sppl/tests/test_parse_spe.py
sppl/tests/test_parse_transforms.py
sppl/tests/test_poly.py
sppl/tests/test_product.py
sppl/tests/test_real_continuous.py
sppl/tests/test_real_discrete.py
sppl/tests/test_render.py
sppl/tests/test_sets.py
sppl/tests/test_solve_transforms.py
sppl/tests/test_spe_to_dict.py
sppl/tests/test_spe_to_spml.py
sppl/tests/test_spe_transform.py
sppl/tests/test_sppl_to_python.py
sppl/tests/test_substitute.py
sppl/tests/test_sum.py
sppl/tests/test_sum_simplify.py
sppl/tests/test_sym_util.py
sppl-2.0.4.dist-info/LICENSE.txt
sppl-2.0.4.dist-info/METADATA
sppl-2.0.4.dist-info/WHEEL
sppl-2.0.4.dist-info/top_level.txt
sppl-2.0.4.dist-info/RECORD
