Metadata-Version: 2.1
Name: sppl
Version: 2.0.4
Summary: The Sum-Product Probabilistic Language
Home-page: https://github.com/probcomp/sppl
Maintainer: Feras A. Saad
Maintainer-email: fsaad@mit.edu
License: Apache-2.0
Platform: UNKNOWN
Classifier: Intended Audience :: Science/Research
Classifier: License :: OSI Approved :: Apache Software License
Classifier: Topic :: Scientific/Engineering :: Mathematics
Requires-Python: >=3.8
Requires-Dist: astunparse (==1.6.3)
Requires-Dist: numpy (==1.22.3)
Requires-Dist: scipy (==1.8.0)
Requires-Dist: sympy (==1.6)
Provides-Extra: all
Requires-Dist: astunparse (==1.6.3) ; extra == 'all'
Requires-Dist: coverage (==5.3) ; extra == 'all'
Requires-Dist: graphviz (==0.13.2) ; extra == 'all'
Requires-Dist: ipython (==7.23.1) ; extra == 'all'
Requires-Dist: jupyter-core (==4.6.3) ; extra == 'all'
Requires-Dist: matplotlib (==3.3.2) ; extra == 'all'
Requires-Dist: networkx (==2.4) ; extra == 'all'
Requires-Dist: notebook (==6.0.3) ; extra == 'all'
Requires-Dist: numpy (==1.22.3) ; extra == 'all'
Requires-Dist: pygraphviz (==1.5) ; extra == 'all'
Requires-Dist: pytest-timeout (==1.3.3) ; extra == 'all'
Requires-Dist: pytest (==5.2.2) ; extra == 'all'
Requires-Dist: scipy (==1.8.0) ; extra == 'all'
Requires-Dist: sympy (==1.6) ; extra == 'all'
Provides-Extra: magics
Requires-Dist: graphviz (==0.13.2) ; extra == 'magics'
Requires-Dist: ipython (==7.23.1) ; extra == 'magics'
Requires-Dist: jupyter-core (==4.6.3) ; extra == 'magics'
Requires-Dist: matplotlib (==3.3.2) ; extra == 'magics'
Requires-Dist: networkx (==2.4) ; extra == 'magics'
Requires-Dist: notebook (==6.0.3) ; extra == 'magics'
Requires-Dist: pygraphviz (==1.5) ; extra == 'magics'
Provides-Extra: src
Requires-Dist: astunparse (==1.6.3) ; extra == 'src'
Requires-Dist: numpy (==1.22.3) ; extra == 'src'
Requires-Dist: scipy (==1.8.0) ; extra == 'src'
Requires-Dist: sympy (==1.6) ; extra == 'src'
Provides-Extra: tests
Requires-Dist: coverage (==5.3) ; extra == 'tests'
Requires-Dist: pytest-timeout (==1.3.3) ; extra == 'tests'
Requires-Dist: pytest (==5.2.2) ; extra == 'tests'
